obstacle_tower_env.py
obstacle_tower_env-4.1.dist-info/LICENSE
obstacle_tower_env-4.1.dist-info/METADATA
obstacle_tower_env-4.1.dist-info/WHEEL
obstacle_tower_env-4.1.dist-info/top_level.txt
obstacle_tower_env-4.1.dist-info/RECORD
