Metadata-Version: 2.1
Name: obstacle-tower-env
Version: 4.1
Summary: UNKNOWN
Home-page: https://github.com/Unity-Technologies/obstacle-tower-env
Author: Unity Technologies
License: UNKNOWN
Platform: UNKNOWN
Requires-Dist: mlagents-envs (<0.19,>=0.17)
Requires-Dist: gym
